Brunfelsia_australis/__init__.py
Brunfelsia_australis/module.py
Brunfelsia_australis-0.1.0.dist-info/LICENSE
Brunfelsia_australis-0.1.0.dist-info/METADATA
Brunfelsia_australis-0.1.0.dist-info/WHEEL
Brunfelsia_australis-0.1.0.dist-info/top_level.txt
Brunfelsia_australis-0.1.0.dist-info/RECORD
