Metadata-Version: 2.1
Name: Brunfelsia-australis
Version: 0.1.0
Summary: A package to find the closest day based on RGB values
Author: Kanon Inuta
Author-email: kanoninuta@gmail.com
Classifier: Programming Language :: Python :: 3
Classifier: License :: OSI Approved :: MIT License
Classifier: Operating System :: OS Independent
Requires-Python: >=3.6
License-File: LICENSE
Requires-Dist: numpy
